bourse-0.4.0.dist-info/METADATA
bourse-0.4.0.dist-info/WHEEL
bourse-0.4.0.dist-info/license_files/LICENSE
bourse/__init__.py
bourse/step_sim/__init__.py
bourse/step_sim/runner.py
bourse/step_sim/agents/random_agent.py
bourse/step_sim/agents/base_agent.py
bourse/step_sim/agents/__init__.py
bourse/data_processing.py
bourse/core.cpython-38-arm-linux-gnueabihf.so
bourse-0.4.0.dist-info/RECORD
