Metadata-Version: 2.3
Name: bourse
Version: 0.4.0
Classifier: License :: OSI Approved :: MIT License
Classifier: Programming Language :: Python
Classifier: Programming Language :: Python :: 3.8
Classifier: Programming Language :: Python :: 3.9
Classifier: Programming Language :: Python :: 3.10
Classifier: Programming Language :: Python :: 3.11
Classifier: Programming Language :: Rust
Classifier: Programming Language :: Python :: Implementation :: CPython
Classifier: Programming Language :: Python :: Implementation :: PyPy
Requires-Dist: tqdm >=4.66.2
Requires-Dist: pandas >=2.2.0
License-File: LICENSE
Summary: Python API for a Rust stock market simulation library
Keywords: finance,agent-based modelling,simulation,reinforcement-learning
Author-email: zombie-einstein <zombie-einstein@proton.me>
Requires-Python: >=3.8
Project-URL: source, https://github.com/zombie-einstein/bourse
Project-URL: docs, https://zombie-einstein.github.io/bourse/
Project-URL: documentation, https://zombie-einstein.github.io/bourse/
